chinese_converter/__init__.py
chinese_converter/bigram.json
chinese_converter/monogram.json
chinese_converter/simplified.txt
chinese_converter/traditional.txt
chinese_converter-1.1.1.dist-info/LICENSE.txt
chinese_converter-1.1.1.dist-info/METADATA
chinese_converter-1.1.1.dist-info/WHEEL
chinese_converter-1.1.1.dist-info/RECORD
