Metadata-Version: 2.1
Name: chinese-converter
Version: 1.1.1
Summary: convert simplified chinese text to traditional chinese
Home-page: https://github.com/zachary822/chinese-converter
License: MIT
Author: Zachary Juang
Author-email: zachary822@me.com
Requires-Python: >=3.10,<4.0
Classifier: License :: OSI Approved :: MIT License
Classifier: Programming Language :: Python :: 3
Classifier: Programming Language :: Python :: 3.10
Classifier: Programming Language :: Python :: 3.11
Project-URL: Repository, https://github.com/zachary822/chinese-converter
